minipub/__init__.py
minipub/admin.py
minipub/managers.py
minipub/models.py
minipub/sitemaps.py
minipub/views.py
scripts/__init__.py
scripts/releaser_hooks.py
django_minipub-1.9.dist-info/LICENSE.txt
django_minipub-1.9.dist-info/METADATA
django_minipub-1.9.dist-info/WHEEL
django_minipub-1.9.dist-info/top_level.txt
django_minipub-1.9.dist-info/RECORD
